src/__init__.py
src/main.py
p2p_ashweenmankash-0.0.1.dist-info/METADATA
p2p_ashweenmankash-0.0.1.dist-info/WHEEL
p2p_ashweenmankash-0.0.1.dist-info/licenses/LICENSE
p2p_ashweenmankash-0.0.1.dist-info/RECORD
